Workbook

Sheet Sheet1
A1: Organization | B1: Resource | C1: Publication year
A2: =Sheet2!A2 -> American Automobile Association (AAA) | B2: =Sheet2!E2 -> <a href="https://gasprices.aaa.com/", target=_blank">National Average Gas Prices.</a> | C2: =Sheet2!C2 -> 2022
A3: =Sheet2!A3 -> Amtrak | B3: =Sheet2!E3 -> <a href="0", target=_blank">FY2019 Monthly Performance Report.</a> | C3: =Sheet2!C3 -> 2019
A4: =Sheet2!A4 -> American Public Transportation Association | B4: =Sheet2!E4 -> <a href="https://www.apta.com/research-technical-resources/transit-statistics/vehicle-database/", target=_blank">Public Transportation Vehicle Database 2019.</a> | C4: =Sheet2!C4 -> 2019
A5: =Sheet2!A5 -> Argonne National Laboratory. GREET | B5: =Sheet2!E5 -> <a href="https://greet.es.anl.gov/", target=_blank">GREET (Greenhouse gases, Regulated Emissions, and Energy use in Technologies Model). Accessed 2021.</a> | C5: =Sheet2!C5 -> 2021
A6: =Sheet2!A6 -> Barr, L.C. | B6: =Sheet2!E6 -> <a href="https://journals.sagepub.com/doi/10.3141/1706-01", target=_blank">Testing for the significance of induced highway travel demand in metropolitan areas. Transportation Research Record: Journal of the Transportation Research Board, vol. 1706.</a> | C6: =Sheet2!C6 -> 2000
A7: =Sheet2!A7 -> California Air Pollution Control Officers Association | B7: =Sheet2!E7 -> <a href="https://www.airquality.org/ClimateChange/Documents/Handbook%20Public%20Draft_2021-Aug.pdf", target=_blank">Handbook for Analyzing Greenhouse Gas Emission Reductions, Assessing Climate Vulnerabilities, and Advancing Health and Equity.</a> | C7: =Sheet2!C7 -> 2021
A8: =Sheet2!A8 -> California Air Resources Board | B8: =Sheet2!E8 -> <a href="https://ww2.arb.ca.gov/sites/default/files/classic/fuels/lcfs/guidance/lcfsguidance_20-04.pdf", target=_blank">Low Carbon Fuel Standard (LCFS) Guidance 20-04 Requesting EER-Adjusted Carbon Intensity Using a Tier 2 Pathway Application.</a> | C8: =Sheet2!C8 -> 2020
A9: =Sheet2!A9 -> Cesme, B., R. Roisman, and D. Miller | B9: =Sheet2!E9 -> <a href="https://journals.sagepub.com/doi/10.1177/0361198118791914", target=_blank">Strategies and Barriers in Effective Bus Lane Implementation and Management: Best Practices for Use in the Greater Washington, D.C. Region. Transportation Research Record 2672:8.</a> | C9: =Sheet2!C9 -> 2018
A10: =Sheet2!A10 -> Coastal Region MPO | B10: =Sheet2!E10 -> <a href="https://www.thempc.org/docs/lit/corempo/studies/parkride/2014/aug/tm5.pdf", target=_blank">Park and Ride Lot Study - Technical Memorandum #5: Financial Analysis and Management Options. Prepared by Connetics Transportation Group, Moffatt & Nichol, and Symbioscity.</a> | C10: =Sheet2!C10 -> 2014
A11: =Sheet2!A11 -> Cambridge Systematics | B11: =Sheet2!E11 -> <a href="https://www.georgetownclimate.org/files/report/GCC_Investment_Tool.pdf", target=_blank">Transportation Investment Strategy Tool Documentation, 2021. Prepared for Georgetown Climate Center.</a> | C11: =Sheet2!C11 -> 2021
A12: =Sheet2!A12 -> Florida Department of Transportation | B12: =Sheet2!E12 -> <a href="https://www.fdot.gov/programmanagement/estimates/documents/costpermilemodelsreports", target=_blank">Cost Per Mile Models Reports. Accessed June 2023.</a> | C12: =Sheet2!C12 -> 2023
A13: =Sheet2!A13 -> Federal Highway Administration | B13: =Sheet2!E13 -> <a href="http://www.pedbikesafe.org/PEDSAFE/index.cfm", target=_blank">PEDSAFE: Pedestrian Safety Guide and Countermeasure Selection System.</a> | C13: =Sheet2!C13 -> 2013
... A43: =Sheet2!A43 -> Weldon Cooper Center for Public Service, Demographics Research Group | B43: =Sheet2!E43 -> <a href="https://demographics.coopercenter.org/population-data-all-overview", target=_blank">National Population Projections.</a> | C43: =Sheet2!C43 -> 2018

Sheet Sheet2
A1: Organization | B1: Resource | C1: Publication year | D1: Link | E1: Name
A2: American Automobile Association (AAA) | B2: National Average Gas Prices. | C2: 2022 | D2: https://gasprices.aaa.com/ | E2: =_xlfn.CONCAT("<a href=",CHAR(34),D2,CHAR(34),", target=_blank",CHAR(34),">",B2,"</a>") -> <a href="https://gasprices.aaa.com/", target=_blank">National Average Gas Prices.</a>
A3: Amtrak | B3: FY2019 Monthly Performance Report. | C3: 2019 | D3: 0 | E3: =_xlfn.CONCAT("<a href=",CHAR(34),D3,CHAR(34),", target=_blank",CHAR(34),">",B3,"</a>") -> <a href="0", target=_blank">FY2019 Monthly Performance Report.</a>
A4: American Public Transportation Association | B4: Public Transportation Vehicle Database 2019. | C4: 2019 | D4: https://www.apta.com/research-technical-resources/transit-statistics/vehicle-database/ | E4: =_xlfn.CONCAT("<a href=",CHAR(34),D4,CHAR(34),", target=_blank",CHAR(34),">",B4,"</a>") -> <a href="https://www.apta.com/research-technical-resources/transit-statistics/vehicle-database/", target=_blank">Public Transportation Vehicle Database 2019.</a>
A5: Argonne National Laboratory. GREET | B5: GREET (Greenhouse gases, Regulated Emissions, and Energy use in Technologies Model). Accessed 2021. | C5: 2021 | D5: https://greet.es.anl.gov/ | E5: =_xlfn.CONCAT("<a href=",CHAR(34),D5,CHAR(34),", target=_blank",CHAR(34),">",B5,"</a>") -> <a href="https://greet.es.anl.gov/", target=_blank">GREET (Greenhouse gases, Regulated Emissions, and Energy use in Technologies Model). Accessed 2021.</a>
A6: Barr, L.C. | B6: Testing for the significance of induced highway travel demand in metropolitan areas. Transportation Research Record: Journal of the Transportation Research Board, vol. 1706. | C6: 2000 | D6: https://journals.sagepub.com/doi/10.3141/1706-01 | E6: =_xlfn.CONCAT("<a href=",CHAR(34),D6,CHAR(34),", target=_blank",CHAR(34),">",B6,"</a>") -> <a href="https://journals.sagepub.com/doi/10.3141/1706-01", target=_blank">Testing for the significance of induced highway travel demand in metropolitan areas. Transportation Research Record: Journal of the Transportation Research Board, vol. 1706.</a>
A7: California Air Pollution Control Officers Association | B7: Handbook for Analyzing Greenhouse Gas Emission Reductions, Assessing Climate Vulnerabilities, and Advancing Health and Equity. | C7: 2021 | D7: https://www.airquality.org/ClimateChange/Documents/Handbook%20Public%20Draft_2021-Aug.pdf | E7: =_xlfn.CONCAT("<a href=",CHAR(34),D7,CHAR(34),", target=_blank",CHAR(34),">",B7,"</a>") -> <a href="https://www.airquality.org/ClimateChange/Documents/Handbook%20Public%20Draft_2021-Aug.pdf", target=_blank">Handbook for Analyzing Greenhouse Gas Emission Reductions, Assessing Climate Vulnerabilities, and Advancing Health and Equity.</a>
A8: California Air Resources Board | B8: Low Carbon Fuel Standard (LCFS) Guidance 20-04 Requesting EER-Adjusted Carbon Intensity Using a Tier 2 Pathway Application. | C8: 2020 | D8: https://ww2.arb.ca.gov/sites/default/files/classic/fuels/lcfs/guidance/lcfsguidance_20-04.pdf | E8: =_xlfn.CONCAT("<a href=",CHAR(34),D8,CHAR(34),", target=_blank",CHAR(34),">",B8,"</a>") -> <a href="https://ww2.arb.ca.gov/sites/default/files/classic/fuels/lcfs/guidance/lcfsguidance_20-04.pdf", target=_blank">Low Carbon Fuel Standard (LCFS) Guidance 20-04 Requesting EER-Adjusted Carbon Intensity Using a Tier 2 Pathway Application.</a>
A9: Cesme, B., R. Roisman, and D. Miller | B9: Strategies and Barriers in Effective Bus Lane Implementation and Management: Best Practices for Use in the Greater Washington, D.C. Region. Transportation Research Record 2672:8. | C9: 2018 | D9: https://journals.sagepub.com/doi/10.1177/0361198118791914 | E9: =_xlfn.CONCAT("<a href=",CHAR(34),D9,CHAR(34),", target=_blank",CHAR(34),">",B9,"</a>") -> <a href="https://journals.sagepub.com/doi/10.1177/0361198118791914", target=_blank">Strategies and Barriers in Effective Bus Lane Implementation and Management: Best Practices for Use in the Greater Washington, D.C. Region. Transportation Research Record 2672:8.</a>
A10: Coastal Region MPO | B10: Park and Ride Lot Study - Technical Memorandum #5: Financial Analysis and Management Options. Prepared by Connetics Transportation Group, Moffatt & Nichol, and Symbioscity. | C10: 2014 | D10: https://www.thempc.org/docs/lit/corempo/studies/parkride/2014/aug/tm5.pdf | E10: =_xlfn.CONCAT("<a href=",CHAR(34),D10,CHAR(34),", target=_blank",CHAR(34),">",B10,"</a>") -> <a href="https://www.thempc.org/docs/lit/corempo/studies/parkride/2014/aug/tm5.pdf", target=_blank">Park and Ride Lot Study - Technical Memorandum #5: Financial Analysis and Management Options. Prepared by Connetics Transportation Group, Moffatt & Nichol, and Symbioscity.</a>
A11: Cambridge Systematics | B11: Transportation Investment Strategy Tool Documentation, 2021. Prepared for Georgetown Climate Center. | C11: 2021 | D11: https://www.georgetownclimate.org/files/report/GCC_Investment_Tool.pdf | E11: =_xlfn.CONCAT("<a href=",CHAR(34),D11,CHAR(34),", target=_blank",CHAR(34),">",B11,"</a>") -> <a href="https://www.georgetownclimate.org/files/report/GCC_Investment_Tool.pdf", target=_blank">Transportation Investment Strategy Tool Documentation, 2021. Prepared for Georgetown Climate Center.</a>
A12: Florida Department of Transportation | B12: Cost Per Mile Models Reports. Accessed June 2023. | C12: 2023 | D12: https://www.fdot.gov/programmanagement/estimates/documents/costpermilemodelsreports | E12: =_xlfn.CONCAT("<a href=",CHAR(34),D12,CHAR(34),", target=_blank",CHAR(34),">",B12,"</a>") -> <a href="https://www.fdot.gov/programmanagement/estimates/documents/costpermilemodelsreports", target=_blank">Cost Per Mile Models Reports. Accessed June 2023.</a>
A13: Federal Highway Administration | B13: PEDSAFE: Pedestrian Safety Guide and Countermeasure Selection System. | C13: 2013 | D13: http://www.pedbikesafe.org/PEDSAFE/index.cfm | E13: =_xlfn.CONCAT("<a href=",CHAR(34),D13,CHAR(34),", target=_blank",CHAR(34),">",B13,"</a>") -> <a href="http://www.pedbikesafe.org/PEDSAFE/index.cfm", target=_blank">PEDSAFE: Pedestrian Safety Guide and Countermeasure Selection System.</a>
A14: Federal Highway Administration | B14: BIKESAFE: Bicycle Safety Guide and Countermeasure Selection System. | C14: 2014 | D14: http://www.pedbikesafe.org/BIKESAFE/index.cfm | E14: =_xlfn.CONCAT("<a href=",CHAR(34),D14,CHAR(34),", target=_blank",CHAR(34),">",B14,"</a>") -> <a href="http://www.pedbikesafe.org/BIKESAFE/index.cfm", target=_blank">BIKESAFE: Bicycle Safety Guide and Countermeasure Selection System.</a>
A15: McGuckin, N. and A. Fucci | B15: Summary of Travel Trends: 2017 National Household Travel Survey. U.S. Department of Transportation, Federal Highway Administration, FHWA-PL-18-019. | C15: 2018 | D15: https://nhts.ornl.gov/assets/2017_nhts_summary_travel_trends.pdf | E15: =_xlfn.CONCAT("<a href=",CHAR(34),D15,CHAR(34),", target=_blank",CHAR(34),">",B15,"</a>") -> <a href="https://nhts.ornl.gov/assets/2017_nhts_summary_travel_trends.pdf", target=_blank">Summary of Travel Trends: 2017 National Household Travel Survey. U.S. Department of Transportation, Federal Highway Administration, FHWA-PL-18-019.</a>
... A21: MacArthur, J., C. Cherry, M. Harpool and D. Scheppke. | B21: A North American Survey of Electric Bicycle Owners. NITC-RR-1041. Portland, OR: Transportation Research and Education Center (TREC). https://dx.doi.org/10.15760/ trec.197 | C21: 2018 | D21: https://pdxscholar.library.pdx.edu/trec_reports/161/ | E21: =_xlfn.CONCAT("<a href=",CHAR(34),D21,CHAR(34),", target=_blank",CHAR(34),">",B21,"</a>") -> <a href="https://pdxscholar.library.pdx.edu/trec_reports/161/", target=_blank">A North American Survey of Electric Bicycle Owners. NITC-RR-1041. Portland, OR: Transportation Research and Education Center (TREC). https://dx.doi.org/10.15760/ trec.197</a>
A22: McGuckin, N. and A. Fucci | B22: Summary of Travel Trends: 2017 National Household Travel Survey. U.S. Department of Transportation, Federal Highway Administration, FHWA-PL-18-019. | C22: 2018 | D22: 0 | E22: =_xlfn.CONCAT("<a href=",CHAR(34),D22,CHAR(34),", target=_blank",CHAR(34),">",B22,"</a>") -> <a href="0", target=_blank">Summary of Travel Trends: 2017 National Household Travel Survey. U.S. Department of Transportation, Federal Highway Administration, FHWA-PL-18-019.</a>
A23: New York City Clean School Bus Coalition | B23: 3 Types of Electric School Buses. | C23: N/A | D23: https://www.nycschoolbus.org/technical-school-bus-need-to-know-1#:~:text=The%20cost%20of%20an%20electric,in%20between%20%2490%2C000%20to%20%24110%2C000. | E23: =_xlfn.CONCAT("<a href=",CHAR(34),D23,CHAR(34),", target=_blank",CHAR(34),">",B23,"</a>") -> <a href="https://www.nycschoolbus.org/technical-school-bus-need-to-know-1#:~:text=The%20cost%20of%20an%20electric,in%20between%20%2490%2C000%20to%20%24110%2C000.", target=_blank">3 Types of Electric School Buses.</a>
A24: NHTS | B24: National Household Travel Survey | C24: 2009 | D24: 0 | E24: =_xlfn.CONCAT("<a href=",CHAR(34),D24,CHAR(34),", target=_blank",CHAR(34),">",B24,"</a>") -> <a href="0", target=_blank">National Household Travel Survey</a>
A25: National Highway Traffic Safety Administration | B25: National Traffic Speeds Survey | C25: 2015 | D25: 0 | E25: =_xlfn.CONCAT("<a href=",CHAR(34),D25,CHAR(34),", target=_blank",CHAR(34),">",B25,"</a>") -> <a href="0", target=_blank">National Traffic Speeds Survey</a>
A26: Mai, T., et al | B26: Electrification Futures Study: Scenarios of Electric Technology Adoption and Power Consumption for the United States. Golden, CO: National Renewable Energy Laboratory. NREL/TP-6A20-71500. | C26: 2018 | D26: https://www.nrel.gov/docs/fy18osti/71500.pdf | E26: =_xlfn.CONCAT("<a href=",CHAR(34),D26,CHAR(34),", target=_blank",CHAR(34),">",B26,"</a>") -> <a href="https://www.nrel.gov/docs/fy18osti/71500.pdf", target=_blank">Electrification Futures Study: Scenarios of Electric Technology Adoption and Power Consumption for the United States. Golden, CO: National Renewable Energy Laboratory. NREL/TP-6A20-71500.</a>
A27: Johnson, C.; E. Nobler, L. Eudy, and M. Jeffers | B27: Financial Analysis of Battery Electric Transit Buses. National Renewable Energy Laboratory Technical Report NREL/TP-5400-74832. | C27: 2020 | D27: https://afdc.energy.gov/files/u/publication/financial_analysis_be_transit_buses.pdf | E27: =_xlfn.CONCAT("<a href=",CHAR(34),D27,CHAR(34),", target=_blank",CHAR(34),">",B27,"</a>") -> <a href="https://afdc.energy.gov/files/u/publication/financial_analysis_be_transit_buses.pdf", target=_blank">Financial Analysis of Battery Electric Transit Buses. National Renewable Energy Laboratory Technical Report NREL/TP-5400-74832.</a>
A28: Hunter, C., et al | B28: Spatial and Temporal Analysis of the Total Cost of Ownership for Class 8 Tractors and Class 4 Parcel Delivery Trucks. National Renewable Energy Laboratory Technical Report NREL/TP-5400-71796. | C28: 2021 | D28: https://www.nrel.gov/docs/fy21osti/71796.pdf | E28: =_xlfn.CONCAT("<a href=",CHAR(34),D28,CHAR(34),", target=_blank",CHAR(34),">",B28,"</a>") -> <a href="https://www.nrel.gov/docs/fy21osti/71796.pdf", target=_blank">Spatial and Temporal Analysis of the Total Cost of Ownership for Class 8 Tractors and Class 4 Parcel Delivery Trucks. National Renewable Energy Laboratory Technical Report NREL/TP-5400-71796.</a>
A29: Federal Transit Administration | B29: National Transit Database | C29: 2019 | D29: https://www.transit.dot.gov/ntd | E29: =_xlfn.CONCAT("<a href=",CHAR(34),D29,CHAR(34),", target=_blank",CHAR(34),">",B29,"</a>") -> <a href="https://www.transit.dot.gov/ntd", target=_blank">National Transit Database</a>
A30: Oak Ridge National Laboratory | B30: Transportation Energy Data Book, Edition 40. | C30: 2022 | D30: https://tedb.ornl.gov/data/ | E30: =_xlfn.CONCAT("<a href=",CHAR(34),D30,CHAR(34),", target=_blank",CHAR(34),">",B30,"</a>") -> <a href="https://tedb.ornl.gov/data/", target=_blank">Transportation Energy Data Book, Edition 40.</a>
A31: Evans, J.E., et al | B31: TCRP Report 95, Traveler Response to Transportation System Changes. Chapter 9: Transit Scheduling and Frequency. Transportation Research Board, Washington, D.C. | C31: 2004 | D31: https://www.trb.org/Publications/TCRPReport95.aspx | E31: =_xlfn.CONCAT("<a href=",CHAR(34),D31,CHAR(34),", target=_blank",CHAR(34),">",B31,"</a>") -> <a href="https://www.trb.org/Publications/TCRPReport95.aspx", target=_blank">TCRP Report 95, Traveler Response to Transportation System Changes. Chapter 9: Transit Scheduling and Frequency. Transportation Research Board, Washington, D.C.</a>
A32: Evans, J.E., and R. H. Pratt, et al | B32: TCRP Report 95, Traveler Response to Transportation System Changes. Chapter 5: Vanpools and Buspools. Transportation Research Board, Washington, D.C. | C32: 2005 | D32: https://www.trb.org/Publications/TCRPReport95.aspx | E32: =_xlfn.CONCAT("<a href=",CHAR(34),D32,CHAR(34),", target=_blank",CHAR(34),">",B32,"</a>") -> <a href="https://www.trb.org/Publications/TCRPReport95.aspx", target=_blank">TCRP Report 95, Traveler Response to Transportation System Changes. Chapter 5: Vanpools and Buspools. Transportation Research Board, Washington, D.C.</a>
A33: [U.K.] Highways Agency | B33: Design Manual for Roads and Bridges, Volume 12, Section 2, Part 2: Induced Traffic Appraisal. | C33: 1997 | D33: 0 | E33: =_xlfn.CONCAT("<a href=",CHAR(34),D33,CHAR(34),", target=_blank",CHAR(34),">",B33,"</a>") -> <a href="0", target=_blank">Design Manual for Roads and Bridges, Volume 12, Section 2, Part 2: Induced Traffic Appraisal.</a>
A34: U.S. Department of Energy, Energy Information Administration | B34: US Electricity Profile 2021. | C34: 2021 | D34: https://www.eia.gov/electricity/state/ | E34: =_xlfn.CONCAT("<a href=",CHAR(34),D34,CHAR(34),", target=_blank",CHAR(34),">",B34,"</a>") -> <a href="https://www.eia.gov/electricity/state/", target=_blank">US Electricity Profile 2021.</a>
A35: U.S. Department of Energy | B35: Annual Energy Outlook Reference Case 2022. Energy Information Administration. | C35: 2022 | D35: https://www.eia.gov/outlooks/aeo/ | E35: =_xlfn.CONCAT("<a href=",CHAR(34),D35,CHAR(34),", target=_blank",CHAR(34),">",B35,"</a>") -> <a href="https://www.eia.gov/outlooks/aeo/", target=_blank">Annual Energy Outlook Reference Case 2022. Energy Information Administration.</a>
A36: U.S. Department of Energy | B36: Annual Energy Outlook Reference Case 2023. Energy Information Administration. | C36: 2023 | D36: https://www.eia.gov/outlooks/aeo/ | E36: =_xlfn.CONCAT("<a href=",CHAR(34),D36,CHAR(34),", target=_blank",CHAR(34),">",B36,"</a>") -> <a href="https://www.eia.gov/outlooks/aeo/", target=_blank">Annual Energy Outlook Reference Case 2023. Energy Information Administration.</a>
A37: U.S. Department of Energy, Alternative Fuels Data Center | B37: Average Fuel Economy by Major Vehicle Category | C37: 2023 | D37: https://afdc.energy.gov/data | E37: =_xlfn.CONCAT("<a href=",CHAR(34),D37,CHAR(34),", target=_blank",CHAR(34),">",B37,"</a>") -> <a href="https://afdc.energy.gov/data", target=_blank">Average Fuel Economy by Major Vehicle Category</a>
A38: U.S. Department of Energy, Alternative Fuels Data Center | B38: Fuel Properties Comparison | C38: 2023 | D38: https://afdc.energy.gov/tools | E38: =_xlfn.CONCAT("<a href=",CHAR(34),D38,CHAR(34),", target=_blank",CHAR(34),">",B38,"</a>") -> <a href="https://afdc.energy.gov/tools", target=_blank">Fuel Properties Comparison</a>
A39: U.S. Department of Transportation | B39: The cost of retiming traffic signals in the Washington, DC area is about $3,500 per intersection. ITS Deployment Evaluation, Intelligent Transportation Systems Joint Program Office. | C39: 2007 | D39: https://www.itskrs.its.dot.gov/its/benecost.nsf/ID/5551ecb16b1bc9698525725f007a75d0 | E39: =_xlfn.CONCAT("<a href=",CHAR(34),D39,CHAR(34),", target=_blank",CHAR(34),">",B39,"</a>") -> <a href="https://www.itskrs.its.dot.gov/its/benecost.nsf/ID/5551ecb16b1bc9698525725f007a75d0", target=_blank">The cost of retiming traffic signals in the Washington, DC area is about $3,500 per intersection. ITS Deployment Evaluation, Intelligent Transportation Systems Joint Program Office.</a>
A40: U.S. Department of Transportation | B40: Transportation's Role in Reducing U.S. Greenhouse Gas Emissions. | C40: 2010 | D40: http://www.reconnectingamerica.org/assets/Uploads/DOTClimateChangeReport-April2010-Volume1and2.pdf | E40: =_xlfn.CONCAT("<a href=",CHAR(34),D40,CHAR(34),", target=_blank",CHAR(34),">",B40,"</a>") -> <a href="http://www.reconnectingamerica.org/assets/Uploads/DOTClimateChangeReport-April2010-Volume1and2.pdf", target=_blank">Transportation's Role in Reducing U.S. Greenhouse Gas Emissions.</a>
A41: U.S. Environmental Protection Agency | B41: GHG Emission Factors Hub. | C41: 2023 | D41: https://www.epa.gov/climateleadership/ghg-emission-factors-hub | E41: =_xlfn.CONCAT("<a href=",CHAR(34),D41,CHAR(34),", target=_blank",CHAR(34),">",B41,"</a>") -> <a href="https://www.epa.gov/climateleadership/ghg-emission-factors-hub", target=_blank">GHG Emission Factors Hub.</a>
A42: Volker, J.N.B., and S.L. Handy | B42: Updating the Induced Travel Calculator. National Center for Sustainable Transportation and UC Davis. | C42: 2022 | D42: https://escholarship.org/uc/item/1hh9b9mf | E42: =_xlfn.CONCAT("<a href=",CHAR(34),D42,CHAR(34),", target=_blank",CHAR(34),">",B42,"</a>") -> <a href="https://escholarship.org/uc/item/1hh9b9mf", target=_blank">Updating the Induced Travel Calculator. National Center for Sustainable Transportation and UC Davis.</a>
A43: Weldon Cooper Center for Public Service, Demographics Research Group | B43: National Population Projections. | C43: 2018 | D43: https://demographics.coopercenter.org/population-data-all-overview | E43: =_xlfn.CONCAT("<a href=",CHAR(34),D43,CHAR(34),", target=_blank",CHAR(34),">",B43,"</a>") -> <a href="https://demographics.coopercenter.org/population-data-all-overview", target=_blank">National Population Projections.</a>
